README.txt
setup.py
cs/__init__.py
cs.linguaplone.links.egg-info/PKG-INFO
cs.linguaplone.links.egg-info/SOURCES.txt
cs.linguaplone.links.egg-info/dependency_links.txt
cs.linguaplone.links.egg-info/entry_points.txt
cs.linguaplone.links.egg-info/namespace_packages.txt
cs.linguaplone.links.egg-info/not-zip-safe
cs.linguaplone.links.egg-info/requires.txt
cs.linguaplone.links.egg-info/top_level.txt
cs/linguaplone/__init__.py
cs/linguaplone/links/__init__.py
cs/linguaplone/links/configure.zcml
cs/linguaplone/links/tests.py
cs/linguaplone/links/version.txt
cs/linguaplone/links/viewlet.pt
cs/linguaplone/links/viewlet.py
docs/HISTORY.txt
docs/INSTALL.txt
docs/LICENSE.GPL
docs/LICENSE.txt