Metadata-Version: 1.1
Name: cs.linguaplone.links
Version: 1.0.2
Summary: A viewlet to write links at HTML <head> tag with links to translations
Home-page: http://code.codesyntax.com/private/cs.linguaplone.links/
Author: Mikel Larreategi
Author-email: mlarreategi@codesyntax.com
License: GPL
Keywords: plone linguaplone i18n links
Platform: UNKNOWN
Classifier: Framework :: Plone
Classifier: Programming Language :: Python
